{ "_id" : 1, "campaign_log" : [], "confirmation_token" : null, "consolidated_contact_id" : null, "created_at" : { "$date" : 1588660889000 }, "current_login" : null, "email" : "admin1@careerlink.vn", "email_candidate" : null, "email_change_requested_at" : null, "enabled" : true, "former_email" : null, "full_name" : "Admin Foo 1", "hashed_password" : "30Egr8Z41/kzjWfUApko01tejEWg+NLWn9ab0RDwtD8XvOhnsfTanA51IKMNdR/yL+FcBVBDrgiOF9xiI7dQSg==", "is_deleted" : false, "is_sales" : true, "last_active" : null, "last_activities" : {}, "last_login" : null, "list_ids" : [], "locked" : false, "oauthUser" : false, "password_requested_at" : null, "preSignUp" : false, "privileges" : { "ACCOUNT" : [ "ALL" ], "ADMIN" : [ "ALL" ], "ADMINNOTE" : [ "ALL" ], "APPLIED_UPLOAD_RESUME" : [ "ALL" ], "BACK_OFFICE_DOC_RESUME" : [ "ALL" ], "CAMPAIGNS" : [ "ALL" ], "COMPANY" : [ "ALL" ], "CONSOLE" : [ "ALL" ], "CONTACT_PERSON" : [ "ALL" ], "CONTACTS" : [ "ALL" ], "CONTENT" : [ "ALL" ], "CRAWLER" : [ "ALL" ], "EMPLOYER" : [ "ALL" ], "EXTERNALRESUME" : [ "ALL" ], "GENERAL" : [ "ALL" ], "JOB" : [ "ALL" ], "JOBSEEKER" : [ "ALL" ], "LOG" : [ "ALL" ], "MASTER" : [ "ALL" ], "RESUME" : [ "ALL" ], "RESUMEACCESS" : [ "ALL" ], "RESUMEACCESSREPORT" : [ "ALL" ], "SALES_TOOL" : [ "ALL" ], "SAVED_RESUME" : [ "ALL" ], "SECURITY_RADAR" : [ "ALL" ], "SITES" : [ "ALL" ] }, "random" : 0.06088059351820526, "salt" : "8b4ng1m95go4scg0ww0s0s00cskw8co", "since" : { "$date" : 1588660889000 }, "sort" : 1, "tag_ids" : [ "confirmed" ], "updated_at" : null, "version" : 0 }
{ "_id" : 2, "campaign_log" : [], "confirmation_token" : null, "consolidated_contact_id" : null, "created_at" : { "$date" : 1588696236000 }, "current_login" : null, "email" : "admin2@careerlink.vn", "email_candidate" : null, "email_change_requested_at" : null, "enabled" : true, "former_email" : null, "full_name" : "Admin Foo 2", "hashed_password" : "rb43RLRLe6glGiyBYFGGvxjec9K5GUwPZedqjuhrnRSzZIzmiKtjHWmDELA7KXYRdBhdaZLg76zePWIGGczsGw==", "is_deleted" : false, "is_sales" : true, "last_active" : null, "last_activities" : {}, "last_login" : null, "list_ids" : [], "locked" : false, "oauthUser" : false, "password_requested_at" : null, "preSignUp" : false, "privileges" : { "ACCOUNT" : [ "ALL" ], "ADMIN" : [ "ALL" ], "ADMINNOTE" : [ "ALL" ], "APPLIED_UPLOAD_RESUME" : [ "ALL" ], "BACK_OFFICE_DOC_RESUME" : [ "ALL" ], "CAMPAIGNS" : [ "ALL" ], "COMPANY" : [ "ALL" ], "CONSOLE" : [ "ALL" ], "CONTACT_PERSON" : [ "ALL" ], "CONTACTS" : [ "ALL" ], "CONTENT" : [ "ALL" ], "CRAWLER" : [ "ALL" ], "EMPLOYER" : [ "ALL" ], "EXTERNALRESUME" : [ "ALL" ], "GENERAL" : [ "ALL" ], "JOB" : [ "ALL" ], "JOBSEEKER" : [ "ALL" ], "LOG" : [ "ALL" ], "MASTER" : [ "ALL" ], "RESUME" : [ "ALL" ], "RESUMEACCESS" : [ "ALL" ], "RESUMEACCESSREPORT" : [ "ALL" ], "SALES_TOOL" : [ "ALL" ], "SAVED_RESUME" : [ "ALL" ], "SECURITY_RADAR" : [ "ALL" ], "SITES" : [ "ALL" ] }, "random" : 0.8284852322323645, "salt" : "af8rq6rq8k8cwkk0800oks08g8ooowo", "since" : { "$date" : 1588696236000 }, "sort" : 2, "tag_ids" : [ "confirmed" ], "updated_at" : null, "version" : 0 }
{ "_id" : 3, "campaign_log" : [], "confirmation_token" : null, "consolidated_contact_id" : null, "created_at" : { "$date" : 1588724219000 }, "current_login" : null, "email" : "admin3@careerlink.vn", "email_candidate" : null, "email_change_requested_at" : null, "enabled" : true, "former_email" : null, "full_name" : "Admin Foo 3", "hashed_password" : "I36s9uXF2DeMTkLjuq4jVtJu2XUVYWtM/QvM3GMCQIDKdUfAwsjeZ9WJX6bsJkw+mZrVgmgFaMoXGS7wVVaNtQ==", "is_deleted" : false, "is_sales" : true, "last_active" : null, "last_activities" : {}, "last_login" : null, "list_ids" : [], "locked" : false, "oauthUser" : false, "password_requested_at" : null, "preSignUp" : false, "privileges" : { "ACCOUNT" : [ "ALL" ], "ADMIN" : [ "ALL" ], "ADMINNOTE" : [ "ALL" ], "APPLIED_UPLOAD_RESUME" : [ "ALL" ], "BACK_OFFICE_DOC_RESUME" : [ "ALL" ], "CAMPAIGNS" : [ "ALL" ], "COMPANY" : [ "ALL" ], "CONSOLE" : [ "ALL" ], "CONTACT_PERSON" : [ "ALL" ], "CONTACTS" : [ "ALL" ], "CONTENT" : [ "ALL" ], "CRAWLER" : [ "ALL" ], "EMPLOYER" : [ "ALL" ], "EXTERNALRESUME" : [ "ALL" ], "GENERAL" : [ "ALL" ], "JOB" : [ "ALL" ], "JOBSEEKER" : [ "ALL" ], "LOG" : [ "ALL" ], "MASTER" : [ "ALL" ], "RESUME" : [ "ALL" ], "RESUMEACCESS" : [ "ALL" ], "RESUMEACCESSREPORT" : [ "ALL" ], "SALES_TOOL" : [ "ALL" ], "SAVED_RESUME" : [ "ALL" ], "SECURITY_RADAR" : [ "ALL" ], "SITES" : [ "ALL" ] }, "random" : 0.8334600617333595, "salt" : "pu9dj21asqo08wocc400gogooksw48w", "since" : { "$date" : 1588724219000 }, "sort" : 3, "tag_ids" : [ "confirmed" ], "updated_at" : null, "version" : 0 }
